wikiusers_cli/__init__.py
wikiusers_cli/__main__.py
wikiusers_cli/main.py
wikiusers_cli/utils/__init__.py
wikiusers_cli/utils/default_values.py
wikiusers_cli/utils/langs.py
wikiusers_cli-1.2.2.dist-info/entry_points.txt
wikiusers_cli-1.2.2.dist-info/LICENSE
wikiusers_cli-1.2.2.dist-info/WHEEL
wikiusers_cli-1.2.2.dist-info/METADATA
wikiusers_cli-1.2.2.dist-info/RECORD
